hamopy/__init__.py
hamopy/algorithm.py
hamopy/classes.py
hamopy/ham_library.py
hamopy/postpro.py
hamopy/examples/BM3_simul.py
hamopy/examples/BM4_simul.py
hamopy/examples/BM5_simul.py
hamopy/examples/__init__.py
hamopy/materials/__init__.py
hamopy/materials/hamstad.py
hamopy/materials/standard.py
hamopy/materials/virtuel.py
hamopy-0.4.0.dist-info/LICENSE.txt
hamopy-0.4.0.dist-info/METADATA
hamopy-0.4.0.dist-info/WHEEL
hamopy-0.4.0.dist-info/top_level.txt
hamopy-0.4.0.dist-info/RECORD
