Metadata-Version: 2.1
Name: hamopy
Version: 0.4.0
Summary: Heat, air and moisture transfer modelling in python
Home-page: http://pypi.python.org/pypi/hamopy/
Author: S. Rouchier
Author-email: simon.rouchier@univ-smb.com
License: LICENSE.txt
Platform: UNKNOWN
